json_and_data/__init__.py
json_and_data/dbify.py
json_and_data/modules/__init__.py
json_and_data-1.0.0.dist-info/LICENSE
json_and_data-1.0.0.dist-info/METADATA
json_and_data-1.0.0.dist-info/WHEEL
json_and_data-1.0.0.dist-info/top_level.txt
json_and_data-1.0.0.dist-info/RECORD
